Technical_Analysis/__init__.py
pandas_stocks_tech_analysis-0.0.2.dist-info/LICENSE
pandas_stocks_tech_analysis-0.0.2.dist-info/METADATA
pandas_stocks_tech_analysis-0.0.2.dist-info/WHEEL
pandas_stocks_tech_analysis-0.0.2.dist-info/top_level.txt
pandas_stocks_tech_analysis-0.0.2.dist-info/RECORD
